bitmex_backtest/__init__.py
bitmex_backtest/bitmex_backtest.py
bitmex_backtest-0.1.3.dist-info/LICENSE.txt
bitmex_backtest-0.1.3.dist-info/METADATA
bitmex_backtest-0.1.3.dist-info/WHEEL
bitmex_backtest-0.1.3.dist-info/top_level.txt
bitmex_backtest-0.1.3.dist-info/RECORD
